pydfscanner/__init__.py
pydfscanner/pydfscanner.py
pydfscanner-1.0.0.dist-info/licenses/LICENSE.txt
pydfscanner-1.0.0.dist-info/METADATA
pydfscanner-1.0.0.dist-info/WHEEL
pydfscanner-1.0.0.dist-info/entry_points.txt
pydfscanner-1.0.0.dist-info/top_level.txt
pydfscanner-1.0.0.dist-info/RECORD
