Metadata-Version: 2.4
Name: pydfscanner
Version: 1.0.0
Summary: PDF scanner and collator
Author-email: Emmet Weyman <emmetweyman@vt.edu>
License: MIT License
Classifier: Programming Language :: Python :: 3
Classifier: Operating System :: POSIX :: Linux
Requires-Python: >=3.11
License-File: LICENSE.txt
Requires-Dist: imutils
Requires-Dist: numpy
Requires-Dist: opencv-python
Requires-Dist: pillow
Requires-Dist: matplotlib
Dynamic: license-file
